[
  {
    "Id": 6001,
    "vsebina": [
      {
        "vrstica": 1,
        "tekst": "Bliža se čas, ko bo, tako kot vsako leto, treba pripraviti spisek "
      },
      {
        "vrstica": 2,
        "tekst": "poslovnih partnerjev, ki jih bomo obdarovali ob koncu leta. Na naslove "
      },
      {
        "vrstica": 3,
        "tekst": "podjetij že prihajajo katalogi, v katerih izdelovalci in prodajalci "
      }
    ],
    "group": {
      "backgroundImage": "Slike/DvanajstaSkupina.png",
      "description": "Tekma 3",
      "groupImage": "Slike/DvanajstaSkupina.png",
      "key": "Tekma3",
      "rank": null,
      "recipesCount": 0,
      "shortTitle": "Tekma3",
      "title": "Tekma 3"
    },
    "zadnjicReseno": null,
    "reseno": false,
    "napake": 0,
    "porabljencas": 0,
    "slika": "Slike/Vaja161.jpg",
    "test": false,
    "crke": [ "<", "n", "i", "v", "o", "h", "r", "u", "p", "a", ":", "4", "5", "d", "B", "A", ">", ",", "f", "e", "k", "c", "č", "t", "l", "+", "/", "-", "0", "1", "%", "H", "z", "D", "s", "g", "M", "F", "d", "8", "C", "R", "O", "m", "x", "6", "3", "2", "K", "E", "Y", "T", "N", "I", "S", "L" ]
  },
  {
    "Id": 6002,
    "vsebina": [
      {
        "vrstica": 1,
        "tekst": "daril predstavljajo letošnjo ponudbo. Kaj torej izbrati za dolgoletnega "
      },
      {
        "vrstica": 2,
        "tekst": "poslovnega partnerja, za katerega vemo, da ima skoraj vse. In kaj podariti "
      },
      {
        "vrstica": 3,
        "tekst": "tujemu partnerju, s katerim smo šele letos navezali poslovne stike, pa "
      }
    ],
    "group": {
      "backgroundImage": "Slike/DvanajstaSkupina.png",
      "description": "Tekma 3",
      "groupImage": "Slike/DvanajstaSkupina.png",
      "key": "Tekma3",
      "rank": null,
      "recipesCount": 0,
      "shortTitle": "Tekma3",
      "title": "Tekma 3"
    },
    "zadnjicReseno": null,
    "reseno": false,
    "napake": 0,
    "porabljencas": 0,
    "slika": "Slike/Vaja161.jpg",
    "test": false,
    "crke": [ "<", "n", "i", "v", "o", "h", "r", "u", "p", "a", ":", "4", "5", "d", "B", "A", ">", ",", "f", "e", "k", "c", "č", "t", "l", "+", "/", "-", "0", "1", "%", "H", "z", "D", "s", "g", "M", "F", "d", "8", "C", "R", "O", "m", "x", "6", "3", "2", "K", "E", "Y", "T", "N", "I", "S", "L" ]
  },
  {
    "Id": 6003,
    "vsebina": [
      {
        "vrstica": 1,
        "tekst": "jih želimo v prihodnje utrditi. Takšna in podobna vprašanja si ponavadi "
      },
      {
        "vrstica": 2,
        "tekst": "zastavljajo tisti, ki v podjetju skrbijo za izbiro in nakup poslovnih "
      },
      {
        "vrstica": 3,
        "tekst": "daril. V nekaterih podjetjih se s tem ukvarja generalni direktor, v drugih "
      }
    ],
    "group": {
      "backgroundImage": "Slike/DvanajstaSkupina.png",
      "description": "Tekma 3",
      "groupImage": "Slike/DvanajstaSkupina.png",
      "key": "Tekma3",
      "rank": null,
      "recipesCount": 0,
      "shortTitle": "Tekma3",
      "title": "Tekma 3"
    },
    "zadnjicReseno": null,
    "reseno": false,
    "napake": 0,
    "porabljencas": 0,
    "slika": "Slike/Vaja161.jpg",
    "test": false,
    "crke": [ "<", "n", "i", "v", "o", "h", "r", "u", "p", "a", ":", "4", "5", "d", "B", "A", ">", ",", "f", "e", "k", "c", "č", "t", "l", "+", "/", "-", "0", "1", "%", "H", "z", "D", "s", "g", "M", "F", "d", "8", "C", "R", "O", "m", "x", "6", "3", "2", "K", "E", "Y", "T", "N", "I", "S", "L" ]
  },
  {
    "Id": 6004,
    "vsebina": [
      {
        "vrstica": 1,
        "tekst": "poslovni sekretar, oddelek za marketing ali komercialisti. Veliko pa je "
      },
      {
        "vrstica": 2,
        "tekst": "tudi podjetij, v katerih je izbira poslovnih daril prepuščena tajnicam. "
      },
      {
        "vrstica": 3,
        "tekst": "Direktorji jim takšno nalogo zaupajo z lahkim srcem, saj vedo, da poznajo "
      }
    ],
    "group": {
      "backgroundImage": "Slike/DvanajstaSkupina.png",
      "description": "Tekma 3",
      "groupImage": "Slike/DvanajstaSkupina.png",
      "key": "Tekma3",
      "rank": null,
      "recipesCount": 0,
      "shortTitle": "Tekma3",
      "title": "Tekma 3"
    },
    "zadnjicReseno": null,
    "reseno": false,
    "napake": 0,
    "porabljencas": 0,
    "slika": "Slike/Vaja161.jpg",
    "test": false,
    "crke": [ "<", "n", "i", "v", "o", "h", "r", "u", "p", "a", ":", "4", "5", "d", "B", "A", ">", ",", "f", "e", "k", "c", "č", "t", "l", "+", "/", "-", "0", "1", "%", "H", "z", "D", "s", "g", "M", "F", "d", "8", "C", "R", "O", "m", "x", "6", "3", "2", "K", "E", "Y", "T", "N", "I", "S", "L" ]
  },
  {
    "Id": 6005,
    "vsebina": [
      {
        "vrstica": 1,
        "tekst": "vse njihove poslovne partnerje. Na svoje tajnice pa se direktorji lahko "
      },
      {
        "vrstica": 2,
        "tekst": "zanesejo tudi zato, ker imajo dober okus. Izbira poslovnega darila ni "
      },
      {
        "vrstica": 3,
        "tekst": "lahka naloga. Vedeti je treba, ali je namenjeno domačemu ali tujemu "
      }
    ],
    "group": {
      "backgroundImage": "Slike/DvanajstaSkupina.png",
      "description": "Tekma 3",
      "groupImage": "Slike/DvanajstaSkupina.png",
      "key": "Tekma3",
      "rank": null,
      "recipesCount": 0,
      "shortTitle": "Tekma3",
      "title": "Tekma 3"
    },
    "zadnjicReseno": null,
    "reseno": false,
    "napake": 0,
    "porabljencas": 0,
    "slika": "Slike/Vaja161.jpg",
    "test": false,
    "crke": [ "<", "n", "i", "v", "o", "h", "r", "u", "p", "a", ":", "4", "5", "d", "B", "A", ">", ",", "f", "e", "k", "c", "č", "t", "l", "+", "/", "-", "0", "1", "%", "H", "z", "D", "s", "g", "M", "F", "d", "8", "C", "R", "O", "m", "x", "6", "3", "2", "K", "E", "Y", "T", "N", "I", "S", "L" ]
  },
  {
    "Id": 6006,
    "vsebina": [
      {
        "vrstica": 1,
        "tekst": "partnerju, kdo ga bo izročil in ob kakšni priložnosti. Pri tem v podjetjih "
      },
      {
        "vrstica": 2,
        "tekst": "pogosto pozabljajo, da si pri načrtovanju in izbiri daril lahko pomagajo "
      },
      {
        "vrstica": 3,
        "tekst": "s seznamom, kaj in komu so podarili lani oziroma v preteklih letih. "
      }
    ],
    "group": {
      "backgroundImage": "Slike/DvanajstaSkupina.png",
      "description": "Tekma 3",
      "groupImage": "Slike/DvanajstaSkupina.png",
      "key": "Tekma3",
      "rank": null,
      "recipesCount": 0,
      "shortTitle": "Tekma3",
      "title": "Tekma 3"
    },
    "zadnjicReseno": null,
    "reseno": false,
    "napake": 0,
    "porabljencas": 0,
    "slika": "Slike/Vaja161.jpg",
    "test": false,
    "crke": [ "<", "n", "i", "v", "o", "h", "r", "u", "p", "a", ":", "4", "5", "d", "B", "A", ">", ",", "f", "e", "k", "c", "č", "t", "l", "+", "/", "-", "0", "1", "%", "H", "z", "D", "s", "g", "M", "F", "d", "8", "C", "R", "O", "m", "x", "6", "3", "2", "K", "E", "Y", "T", "N", "I", "S", "L" ]
  },
  {
    "Id": 6007,
    "vsebina": [
      {
        "vrstica": 1,
        "tekst": "Takšen seznam priporočajo tudi poznavalci, ki se poklicno ukvarjajo s "
      },
      {
        "vrstica": 2,
        "tekst": "svetovanjem o poslovnih darilih in protokolu obdarovanja. Veliko podjetij "
      },
      {
        "vrstica": 3,
        "tekst": "ob posebnih poslovnih priložnostih, kot so podpisi pomembnih pogodb, "
      }
    ],
    "group": {
      "backgroundImage": "Slike/DvanajstaSkupina.png",
      "description": "Tekma 3",
      "groupImage": "Slike/DvanajstaSkupina.png",
      "key": "Tekma3",
      "rank": null,
      "recipesCount": 0,
      "shortTitle": "Tekma3",
      "title": "Tekma 3"
    },
    "zadnjicReseno": null,
    "reseno": false,
    "napake": 0,
    "porabljencas": 0,
    "slika": "Slike/Vaja161.jpg",
    "test": false,
    "crke": [ "<", "n", "i", "v", "o", "h", "r", "u", "p", "a", ":", "4", "5", "d", "B", "A", ">", ",", "f", "e", "k", "c", "č", "t", "l", "+", "/", "-", "0", "1", "%", "H", "z", "D", "s", "g", "M", "F", "d", "8", "C", "R", "O", "m", "x", "6", "3", "2", "K", "E", "Y", "T", "N", "I", "S", "L" ]
  },
  {
    "Id": 6008,
    "vsebina": [
      {
        "vrstica": 1,
        "tekst": "obisk partnerjev ali drugih dogodkih najame takšne poklicne svetovalce. "
      },
      {
        "vrstica": 2,
        "tekst": "Ti pripravljajo tudi posebne seminarje o poslovnem obdarovanju, namenjene "
      },
      {
        "vrstica": 3,
        "tekst": "vsem, ki v podjetju skrbijo za poslovna darila, torej tudi tajnicam. "
      }
    ],
    "group": {
      "backgroundImage": "Slike/DvanajstaSkupina.png",
      "description": "Tekma 3",
      "groupImage": "Slike/DvanajstaSkupina.png",
      "key": "Tekma3",
      "rank": null,
      "recipesCount": 0,
      "shortTitle": "Tekma3",
      "title": "Tekma 3"
    },
    "zadnjicReseno": null,
    "reseno": false,
    "napake": 0,
    "porabljencas": 0,
    "slika": "Slike/Vaja161.jpg",
    "test": false,
    "crke": [ "<", "n", "i", "v", "o", "h", "r", "u", "p", "a", ":", "4", "5", "d", "B", "A", ">", ",", "f", "e", "k", "c", "č", "t", "l", "+", "/", "-", "0", "1", "%", "H", "z", "D", "s", "g", "M", "F", "d", "8", "C", "R", "O", "m", "x", "6", "3", "2", "K", "E", "Y", "T", "N", "I", "S", "L" ]
  },
  {
    "Id": 6009,
    "vsebina": [
      {
        "vrstica": 1,
        "tekst": "Svetovalci trdijo, da je poslovno obdarovanje postalo že prava mala veda. "
      },
      {
        "vrstica": 2,
        "tekst": "Ta med drugim razvršča darila glede na njihovo primernost. Najprimernejše "
      },
      {
        "vrstica": 3,
        "tekst": "darilo poslovnemu partnerju je po mnenju večine lasten izdelek tovarne "
      }
    ],
    "group": {
      "backgroundImage": "Slike/DvanajstaSkupina.png",
      "description": "Tekma 3",
      "groupImage": "Slike/DvanajstaSkupina.png",
      "key": "Tekma3",
      "rank": null,
      "recipesCount": 0,
      "shortTitle": "Tekma3",
      "title": "Tekma 3"
    },
    "zadnjicReseno": null,
    "reseno": false,
    "napake": 0,
    "porabljencas": 0,
    "slika": "Slike/Vaja161.jpg",
    "test": false,
    "crke": [ "<", "n", "i", "v", "o", "h", "r", "u", "p", "a", ":", "4", "5", "d", "B", "A", ">", ",", "f", "e", "k", "c", "č", "t", "l", "+", "/", "-", "0", "1", "%", "H", "z", "D", "s", "g", "M", "F", "d", "8", "C", "R", "O", "m", "x", "6", "3", "2", "K", "E", "Y", "T", "N", "I", "S", "L" ]
  },
  {
    "Id": 6010,
    "vsebina": [
      {
        "vrstica": 1,
        "tekst": "ali podjetja, ki naj bo lično zavit. Druga primerna darila so izdelki "
      },
      {
        "vrstica": 2,
        "tekst": "kulturne dediščine, likovna dela, knjige, zgoščenke z glasbo, sodobno "
      },
      {
        "vrstica": 3,
        "tekst": "oblikovani uporabni ali okrasni izdelki, kulinarika, pisarniška darila, "
      }
    ],
    "group": {
      "backgroundImage": "Slike/DvanajstaSkupina.png",
      "description": "Tekma 3",
      "groupImage": "Slike/DvanajstaSkupina.png",
      "key": "Tekma3",
      "rank": null,
      "recipesCount": 0,
      "shortTitle": "Tekma3",
      "title": "Tekma 3"
    },
    "zadnjicReseno": null,
    "reseno": false,
    "napake": 0,
    "porabljencas": 0,
    "slika": "Slike/Vaja161.jpg",
    "test": false,
    "crke": [ "<", "n", "i", "v", "o", "h", "r", "u", "p", "a", ":", "4", "5", "d", "B", "A", ">", ",", "f", "e", "k", "c", "č", "t", "l", "+", "/", "-", "0", "1", "%", "H", "z", "D", "s", "g", "M", "F", "d", "8", "C", "R", "O", "m", "x", "6", "3", "2", "K", "E", "Y", "T", "N", "I", "S", "L" ]
  },
  {
    "Id": 6011,
    "vsebina": [
      {
        "vrstica": 1,
        "tekst": "kozmetika ali celo rezano cvetje in sestavljena praktična darila. Ponudba "
      },
      {
        "vrstica": 2,
        "tekst": "različnih daril je na slovenskem trgu sicer že dokaj pestra, vendar še "
      },
      {
        "vrstica": 3,
        "tekst": "vedno ni tako bogata kot v bolj razvitih državah. V Angliji in Nemčiji "
      }
    ],
    "group": {
      "backgroundImage": "Slike/DvanajstaSkupina.png",
      "description": "Tekma 3",
      "groupImage": "Slike/DvanajstaSkupina.png",
      "key": "Tekma3",
      "rank": null,
      "recipesCount": 0,
      "shortTitle": "Tekma3",
      "title": "Tekma 3"
    },
    "zadnjicReseno": null,
    "reseno": false,
    "napake": 0,
    "porabljencas": 0,
    "slika": "Slike/Vaja161.jpg",
    "test": false,
    "crke": [ "<", "n", "i", "v", "o", "h", "r", "u", "p", "a", ":", "4", "5", "d", "B", "A", ">", ",", "f", "e", "k", "c", "č", "t", "l", "+", "/", "-", "0", "1", "%", "H", "z", "D", "s", "g", "M", "F", "d", "8", "C", "R", "O", "m", "x", "6", "3", "2", "K", "E", "Y", "T", "N", "I", "S", "L" ]
  },
  {
    "Id": 6012,
    "vsebina": [
      {
        "vrstica": 1,
        "tekst": "so najbolj cenjena darila, ki so sinteza sodobne ustvarjalnosti in "
      },
      {
        "vrstica": 2,
        "tekst": "kulturne dediščine. Takšna darila so za zdaj pri nas bolj izjema kot "
      },
      {
        "vrstica": 3,
        "tekst": "pravilo. Pri poslovnih darilih sta skoraj enako pomembna izbor "
      }
    ],
    "group": {
      "backgroundImage": "Slike/DvanajstaSkupina.png",
      "description": "Tekma 3",
      "groupImage": "Slike/DvanajstaSkupina.png",
      "key": "Tekma3",
      "rank": null,
      "recipesCount": 0,
      "shortTitle": "Tekma3",
      "title": "Tekma 3"
    },
    "zadnjicReseno": null,
    "reseno": false,
    "napake": 0,
    "porabljencas": 0,
    "slika": "Slike/Vaja161.jpg",
    "test": false,
    "crke": [ "<", "n", "i", "v", "o", "h", "r", "u", "p", "a", ":", "4", "5", "d", "B", "A", ">", ",", "f", "e", "k", "c", "č", "t", "l", "+", "/", "-", "0", "1", "%", "H", "z", "D", "s", "g", "M", "F", "d", "8", "C", "R", "O", "m", "x", "6", "3", "2", "K", "E", "Y", "T", "N", "I", "S", "L" ]
  },
  {
    "Id": 6013,
    "vsebina": [
      {
        "vrstica": 1,
        "tekst": "primernega darila in embalaža. V zadnjih letih je bilo najbolj modno "
      },
      {
        "vrstica": 2,
        "tekst": "zavijanje daril v valovito lepenko. Zdaj pa je na pohodu, kot pravijo "
      },
      {
        "vrstica": 3,
        "tekst": "nekateri poznavalci modnih trendov, zavijanje v bleščeč papir in zlate "
      }
    ],
    "group": {
      "backgroundImage": "Slike/DvanajstaSkupina.png",
      "description": "Tekma 3",
      "groupImage": "Slike/DvanajstaSkupina.png",
      "key": "Tekma3",
      "rank": null,
      "recipesCount": 0,
      "shortTitle": "Tekma3",
      "title": "Tekma 3"
    },
    "zadnjicReseno": null,
    "reseno": false,
    "napake": 0,
    "porabljencas": 0,
    "slika": "Slike/Vaja161.jpg",
    "test": false,
    "crke": [ "<", "n", "i", "v", "o", "h", "r", "u", "p", "a", ":", "4", "5", "d", "B", "A", ">", ",", "f", "e", "k", "c", "č", "t", "l", "+", "/", "-", "0", "1", "%", "H", "z", "D", "s", "g", "M", "F", "d", "8", "C", "R", "O", "m", "x", "6", "3", "2", "K", "E", "Y", "T", "N", "I", "S", "L" ]
  },
  {
    "Id": 6014,
    "vsebina": [
      {
        "vrstica": 1,
        "tekst": "škatle. Tak slog naj bi naznanjal prihod novega tisočletja. Toda nekateri "
      },
      {
        "vrstica": 2,
        "tekst": "menijo, da je zavijanje v bleščeč papir le trenutna modna muha, ki bo "
      },
      {
        "vrstica": 3,
        "tekst": "izginila še pred prihodom tretjega tisočletja. Primerno darilo za domače "
      }
    ],
    "group": {
      "backgroundImage": "Slike/DvanajstaSkupina.png",
      "description": "Tekma 3",
      "groupImage": "Slike/DvanajstaSkupina.png",
      "key": "Tekma3",
      "rank": null,
      "recipesCount": 0,
      "shortTitle": "Tekma3",
      "title": "Tekma 3"
    },
    "zadnjicReseno": null,
    "reseno": false,
    "napake": 0,
    "porabljencas": 0,
    "slika": "Slike/Vaja161.jpg",
    "test": false,
    "crke": [ "<", "n", "i", "v", "o", "h", "r", "u", "p", "a", ":", "4", "5", "d", "B", "A", ">", ",", "f", "e", "k", "c", "č", "t", "l", "+", "/", "-", "0", "1", "%", "H", "z", "D", "s", "g", "M", "F", "d", "8", "C", "R", "O", "m", "x", "6", "3", "2", "K", "E", "Y", "T", "N", "I", "S", "L" ]
  },
  {
    "Id": 6015,
    "vsebina": [
      {
        "vrstica": 1,
        "tekst": "in tuje poslovne partnerje so tudi knjige, zlasti tiste, ki predstavljajo "
      },
      {
        "vrstica": 2,
        "tekst": "slovensko literaturo in likovno umetnost. Čeprav ponudba takšnih knjig, "
      },
      {
        "vrstica": 3,
        "tekst": "izdanih celo v več tujih jezikih, na našem trgu ni prav velika, je vendar "
      }
    ],
    "group": {
      "backgroundImage": "Slike/DvanajstaSkupina.png",
      "description": "Tekma 3",
      "groupImage": "Slike/DvanajstaSkupina.png",
      "key": "Tekma3",
      "rank": null,
      "recipesCount": 0,
      "shortTitle": "Tekma3",
      "title": "Tekma 3"
    },
    "zadnjicReseno": null,
    "reseno": false,
    "napake": 0,
    "porabljencas": 0,
    "slika": "Slike/Vaja161.jpg",
    "test": false,
    "crke": [ "<", "n", "i", "v", "o", "h", "r", "u", "p", "a", ":", "4", "5", "d", "B", "A", ">", ",", "f", "e", "k", "c", "č", "t", "l", "+", "/", "-", "0", "1", "%", "H", "z", "D", "s", "g", "M", "F", "d", "8", "C", "R", "O", "m", "x", "6", "3", "2", "K", "E", "Y", "T", "N", "I", "S", "L" ]
  },
  {
    "Id": 6016,
    "vsebina": [
      {
        "vrstica": 1,
        "tekst": "mogoče najti nekaj zanimivih. Obdarovanje z vini se je pri nas tudi zelo v modi. "
      },
      {
        "vrstica": 2,
        "tekst": null
      },
      {
        "vrstica": 3,
        "tekst": null
      }
    ],
    "group": {
      "backgroundImage": "Slike/DvanajstaSkupina.png",
      "description": "Tekma 3",
      "groupImage": "Slike/DvanajstaSkupina.png",
      "key": "Tekma3",
      "rank": null,
      "recipesCount": 0,
      "shortTitle": "Tekma3",
      "title": "Tekma 3"
    },
    "zadnjicReseno": null,
    "reseno": false,
    "napake": 0,
    "porabljencas": 0,
    "slika": "Slike/Vaja161.jpg",
    "test": false,
    "crke": [ "<", "n", "i", "v", "o", "h", "r", "u", "p", "a" ]
  }
]